custom_materializations/__init__.py
custom_materializations/full.py
custom_materializations-0.0.0.dist-info/METADATA
custom_materializations-0.0.0.dist-info/WHEEL
custom_materializations-0.0.0.dist-info/entry_points.txt
custom_materializations-0.0.0.dist-info/top_level.txt
custom_materializations-0.0.0.dist-info/RECORD
