Metadata-Version: 2.1
Name: custom-materializations
Version: 0.0.0
Requires-Dist: sqlmesh
